LICENSE
setup.py
avispa_lattices/AL.py
avispa_lattices/__init__.py
avispa_lattices/function_iteration.py
avispa_lattices/function_operations.py
avispa_lattices/lattice_iteration.py
avispa_lattices.egg-info/PKG-INFO
avispa_lattices.egg-info/SOURCES.txt
avispa_lattices.egg-info/dependency_links.txt
avispa_lattices.egg-info/requires.txt
avispa_lattices.egg-info/top_level.txt
avispa_lattices/lattice/__init__.py
avispa_lattices/lattice/description.py
avispa_lattices/lattice/downsets.py
avispa_lattices/lattice/graph.py
avispa_lattices/lattice/identity.py
avispa_lattices/lattice/interface.py
avispa_lattices/lattice/lattice.py
avispa_lattices/lattice/random_function.py
avispa_lattices/lattice/validation.py
avispa_lattices/package_info/_PACKAGES.py
avispa_lattices/package_info/_REQUIREMENTS.py
avispa_lattices/package_info/_VERSION.py
avispa_lattices/package_info/__init__.py
avispa_lattices/random_lattice/__init__.py
avispa_lattices/random_lattice/czech_algorithm.py
avispa_lattices/random_lattice/random_lattice.py
avispa_lattices/testing/__init__.py
avispa_lattices/testing/test.py
avispa_lattices/testing/test_downsets.py
avispa_lattices/testing/test_generation_until_7.py
avispa_lattices/testing/test_package_info.py
avispa_lattices/testing/vtest3.py
avispa_lattices/testing/vtest_1.py
avispa_lattices/testing/vtest_random_f.py
avispa_lattices/utils/__init__.py
avispa_lattices/utils/_enum.py
avispa_lattices/utils/_function_types.py
avispa_lattices/utils/algorithm_floyd_warshall.py
avispa_lattices/utils/algorithm_tarjan.py
avispa_lattices/utils/iterators.py
avispa_lattices/utils/methodtools.py
avispa_lattices/utils/numpy_types.py
avispa_lattices/utils/random_state.py
avispa_lattices/visualization/__init__.py
avispa_lattices/visualization/graphviz.py
avispa_lattices/visualization/gui.py