Metadata-Version: 2.1
Name: avispa-lattices
Version: 3.0.31
Summary: Toolbox for finite lattices
Home-page: https://github.com/caph1993/avispa-lattices
Author: Carlos Pinzón
Author-email: caph1993@gmail.com
License: MIT
Platform: UNKNOWN
Classifier: Development Status :: 1 - Planning
Classifier: Intended Audience :: Science/Research
Classifier: License :: OSI Approved :: BSD License
Classifier: Operating System :: POSIX :: Linux
Classifier: Programming Language :: Python :: 3
Classifier: Programming Language :: Python :: 3.6
License-File: LICENSE
